[{
    "name": "首页",
    "icon": "&#xe68e;",
    "url": "/adminindex",
    "hidden": false,
    "list": []
}, {
    "name": "用户管理",
    "icon": "&#xe612;",
    "url": "",
    "hidden": false,
    "list": [{
        "name": "用户列表",
        "url": "/userlist"
    }, {
        "name": "用户反馈",
        "url": "/userfk"
    }]
}, {
    "name": "文章管理",
    "icon": "&#xe609;",
    "url": "",
    "hidden": false,
    "list": [{
        "name": "类别管理",
        "url": "/admintypeindex"
    }, {
        "name": "文章管理",
        "url": "/articleindex"
    }]
}, {
    "name": "管理员",
    "icon": "&#xe620;",
    "url": "",
    "hidden": false,
    "list": [{
        "name": "管理员列表",
        "url": "/adminlist"
    }]
}, {
    "name": "公告管理",
    "icon": "&#xe857;",
    "url": "",
    "hidden": false,
    "list": [{
        "name": "修改公告",
        "url": "gg_add"
    }]
}, {
    "name": "退出登录",
    "icon": "&#xe65c;",
    "url": "/out",
    "list": []
}]